django_blog_api/__init__.py
django_blog_api/comments/__init__.py
django_blog_api/comments/admin.py
django_blog_api/comments/apps.py
django_blog_api/comments/models.py
django_blog_api/comments/tests.py
django_blog_api/comments/views.py
django_blog_api/comments/api/__init__.py
django_blog_api/comments/api/urls.py
django_blog_api/comments/api/views.py
django_blog_api/comments/migrations/__init__.py
django_blog_api/config/__init__.py
django_blog_api/config/api/__init__.py
django_blog_api/config/api/urls.py
django_blog_api/posts/__init__.py
django_blog_api/posts/__main__.py
django_blog_api/posts/admin.py
django_blog_api/posts/apps.py
django_blog_api/posts/models.py
django_blog_api/posts/tests.py
django_blog_api/posts/views.py
django_blog_api/posts/api/__init__.py
django_blog_api/posts/api/urls.py
django_blog_api/posts/api/views.py
django_blog_api/posts/migrations/0001_initial.py
django_blog_api/posts/migrations/0002_post_titlee.py
django_blog_api/posts/migrations/0003_post_titleee.py
django_blog_api/posts/migrations/0004_post_titleeee.py
django_blog_api/posts/migrations/__init__.py
django_blog_api-0.0.6.dist-info/LICENSE
django_blog_api-0.0.6.dist-info/METADATA
django_blog_api-0.0.6.dist-info/WHEEL
django_blog_api-0.0.6.dist-info/entry_points.txt
django_blog_api-0.0.6.dist-info/top_level.txt
django_blog_api-0.0.6.dist-info/RECORD
